{
  "common": {
    "noOpenPosition": "Nenhuma posição aberta"
  },
  "stats": {
    "supplyBalance": "Fornecimento Total",
    "netAPY": "APY líquido",
    "norrowBalance": "Total emprestado"
  },
  "loans": {
    "title": "Meus empréstimos",
    "collection": "Coleção",
    "currentFloorPrice": "Preço mínimo",
    "collateralValue": "Valor da garantia",
    "activeCollaterals": "Garantias Ativas",
    "borrowBalance": "Seu Emprestado",
    "liquidationPrice": "Preço de liquidação",
    "healthFactor": "Fator de Saúde",
    "functionButtons": "Açao"
  },
  "supplies": {
    "title": "Meus suprimentos",
    "symbol": "Bens",
    "APY": "APY",
    "underlyingBalance": "Saldo de fornecimento",
    "walletBalance": "Saldo da carteira",
    "functionButtons": "Açao"
  }
}