{
  "title": "Blocco NFT",
  "subTitle": "Blocca i tuoi NFT per i premi in token VCI.",
  "Card": {
    "totalValueLocked": "Valore totale bloccato",
    "totalLockedNFT": "NFT totale bloccato",
    "userLockedNFT": "Il tuo NFT bloccato",
    "rewardAPR": "Ricompensa aprile",
    "estmatedRewards": "Premi stimati"
  },
  "NFTLockdropRewards": {
    "title": "Premi Lockdrop NFT",
    "subTitle": {
      "text": "Blocca i tuoi NFT per i premi in token VCI",
      "tip": "Scopri di più"
    },
    "collection": "Collezione",
    "TVL": "TVL",
    "totalLockedNFT": "NFT totale bloccato",
    "userLockedNFT": "Il tuo NFT bloccato",
    "estmatedRewards": "Premi stimati",
    "functionButtons": "Azione",
    "actions": {
      "depositNFT": "Blocca NFT"
    }
  }
}